convertion/__init__.py
convertion/__main__.py
convertion-0.0.3.dist-info/LICENSE
convertion-0.0.3.dist-info/WHEEL
convertion-0.0.3.dist-info/METADATA
convertion-0.0.3.dist-info/RECORD
