Metadata-Version: 2.1
Name: convertion
Version: 0.0.3
Summary: convert all .doc, .docx, .xls, .xlsx, .ppt, and .pptx files to PDF at once
Author-email: calcuis <info@calcu.io>
Classifier: License :: OSI Approved :: MIT License
Requires-Dist: pywin32
Project-URL: Homepage, https://github.com/calcuis/convertion
Project-URL: Issues, https://github.com/calcuis/convertion/issues
